{
  "item": [
    {
      "id": "01cfa467-0cc0-4e2f-a294-95bd3ded4451",
      "name": "Authentication",
      "description": {
        "content": "OAuth 2.0 client-credentials token issuance",
        "type": "text/plain"
      },
      "item": [
        {
          "id": "8512347e-7e07-4c6a-ba2c-9fcc8c36b7c9",
          "name": "Lean Generate Access Token",
          "request": {
            "name": "Lean Generate Access Token",
            "description": {
              "content": "Exchange client_id and client_secret for a JWT access token. Use scope=api for backend API calls or scope=customer.<customer_id> for the LinkSDK.\n",
              "type": "text/plain"
            },
            "url": {
              "path": [
                "oauth2",
                "token"
              ],
              "host": [
                "{{baseUrl}}"
              ],
              "query": [],
              "variable": []
            },
            "header": [
              {
                "key": "Content-Type",
                "value": "application/x-www-form-urlencoded"
              },
              {
                "key": "Accept",
                "value": "application/json"
              }
            ],
            "method": "POST",
            "auth": null,
            "body": {
              "mode": "urlencoded",
              "urlencoded": [
                {
                  "disabled": false,
                  "key": "client_id",
                  "value": "<string>",
                  "description": "(Required) Application ID from the Lean Application Dashboard."
                },
                {
                  "disabled": false,
                  "key": "client_secret",
                  "value": "<string>",
                  "description": "(Required) Client secret from the Lean Application Dashboard."
                },
                {
                  "disabled": false,
                  "key": "grant_type",
                  "value": "<string>",
                  "description": "(Required) "
                },
                {
                  "disabled": false,
                  "key": "scope",
                  "value": "<string>",
                  "description": "(Required) api for backend access, or customer.<customer_id> for SDK access."
                }
              ]
            }
          },
          "response": [
            {
              "id": "f6692a1b-4d09-4940-a352-4a0160489076",
              "name": "Token issued successfully",
              "originalRequest": {
                "url": {
                  "path": [
                    "oauth2",
                    "token"
                  ],
                  "host": [
                    "{{baseUrl}}"
                  ],
                  "query": [],
                  "variable": []
                },
                "header": [
                  {
                    "key": "Accept",
                    "value": "application/json"
                  }
                ],
                "method": "POST",
                "body": {
                  "mode": "urlencoded",
                  "urlencoded": [
                    {
                      "disabled": false,
                      "description": {
                        "content": "(Required) Application ID from the Lean Application Dashboard.",
                        "type": "text/plain"
                      },
                      "key": "client_id",
                      "value": "<string>"
                    },
                    {
                      "disabled": false,
                      "description": {
                        "content": "(Required) Client secret from the Lean Application Dashboard.",
                        "type": "text/plain"
                      },
                      "key": "client_secret",
                      "value": "<string>"
                    },
                    {
                      "disabled": false,
                      "description": {
                        "content": "(Required) ",
                        "type": "text/plain"
                      },
                      "key": "grant_type",
                      "value": "<string>"
                    },
                    {
                      "disabled": false,
                      "description": {
                        "content": "(Required) api for backend access, or customer.<customer_id> for SDK access.",
                        "type": "text/plain"
                      },
                      "key": "scope",
                      "value": "api"
                    }
                  ]
                }
              },
              "status": "OK",
              "code": 200,
              "header": [
                {
                  "key": "Content-Type",
                  "value": "application/json"
                }
              ],
              "body": "{\n  \"access_token\": \"string\",\n  \"token_type\": \"bearer\",\n  \"expires_in\": 4955\n}",
              "cookie": [],
              "_postman_previewlanguage": "json"
            },
            {
              "id": "0f4fb270-fbc6-4489-ae24-824793a20f32",
              "name": "Invalid request",
              "originalRequest": {
                "url": {
                  "path": [
                    "oauth2",
                    "token"
                  ],
                  "host": [
                    "{{baseUrl}}"
                  ],
                  "query": [],
                  "variable": []
                },
                "method": "POST",
                "body": {
                  "mode": "urlencoded",
                  "urlencoded": [
                    {
                      "disabled": false,
                      "description": {
                        "content": "(Required) Application ID from the Lean Application Dashboard.",
                        "type": "text/plain"
                      },
                      "key": "client_id",
                      "value": "<string>"
                    },
                    {
                      "disabled": false,
                      "description": {
                        "content": "(Required) Client secret from the Lean Application Dashboard.",
                        "type": "text/plain"
                      },
                      "key": "client_secret",
                      "value": "<string>"
                    },
                    {
                      "disabled": false,
                      "description": {
                        "content": "(Required) ",
                        "type": "text/plain"
                      },
                      "key": "grant_type",
                      "value": "<string>"
                    },
                    {
                      "disabled": false,
                      "description": {
                        "content": "(Required) api for backend access, or customer.<customer_id> for SDK access.",
                        "type": "text/plain"
                      },
                      "key": "scope",
                      "value": "api"
                    }
                  ]
                }
              },
              "status": "Bad Request",
              "code": 400,
              "header": [
                {
                  "key": "Content-Type",
                  "value": "text/plain"
                }
              ],
              "body": "",
              "cookie": [],
              "_postman_previewlanguage": "text"
            },
            {
              "id": "daf78a90-e1ff-4f19-b49d-b18f78a36bde",
              "name": "Invalid credentials",
              "originalRequest": {
                "url": {
                  "path": [
                    "oauth2",
                    "token"
                  ],
                  "host": [
                    "{{baseUrl}}"
                  ],
                  "query": [],
                  "variable": []
                },
                "method": "POST",
                "body": {
                  "mode": "urlencoded",
                  "urlencoded": [
                    {
                      "disabled": false,
                      "description": {
                        "content": "(Required) Application ID from the Lean Application Dashboard.",
                        "type": "text/plain"
                      },
                      "key": "client_id",
                      "value": "<string>"
                    },
                    {
                      "disabled": false,
                      "description": {
                        "content": "(Required) Client secret from the Lean Application Dashboard.",
                        "type": "text/plain"
                      },
                      "key": "client_secret",
                      "value": "<string>"
                    },
                    {
                      "disabled": false,
                      "description": {
                        "content": "(Required) ",
                        "type": "text/plain"
                      },
                      "key": "grant_type",
                      "value": "<string>"
                    },
                    {
                      "disabled": false,
                      "description": {
                        "content": "(Required) api for backend access, or customer.<customer_id> for SDK access.",
                        "type": "text/plain"
                      },
                      "key": "scope",
                      "value": "api"
                    }
                  ]
                }
              },
              "status": "Unauthorized",
              "code": 401,
              "header": [
                {
                  "key": "Content-Type",
                  "value": "text/plain"
                }
              ],
              "body": "",
              "cookie": [],
              "_postman_previewlanguage": "text"
            }
          ],
          "event": [],
          "protocolProfileBehavior": {
            "disableBodyPruning": true
          }
        }
      ],
      "event": []
    }
  ],
  "event": [],
  "variable": [
    {
      "type": "string",
      "value": "https://auth.leantech.me",
      "key": "baseUrl"
    }
  ],
  "info": {
    "_postman_id": "9dfd4927-1657-408a-a959-947e70c0f5d5",
    "name": "Lean Authentication API",
    "schema": "https://schema.getpostman.com/json/collection/v2.1.0/collection.json",
    "description": {
      "content": "OAuth 2.0 client-credentials token issuance for Lean APIs. Generates two classes of JWT access token: (1) scope=api for server-to-server backend calls, and (2) scope=customer.<customer_id> for the LinkSDK to act on behalf of an end-user. All tokens must be generated from a secure backend using credentials issued in the Lean Application Dashboard.\n\n\nContact Support:\n Name: Lean Support",
      "type": "text/plain"
    }
  }
}