{
  "item": [
    {
      "id": "683e8c8f-25f2-4283-9b99-d976cc69d8b1",
      "name": "Refunds",
      "description": {
        "content": "",
        "type": "text/plain"
      },
      "item": [
        {
          "id": "22b3afdf-58f1-4bcc-a9d3-0d59ee5eb1f9",
          "name": "Lean List Refunds",
          "request": {
            "name": "Lean List Refunds",
            "description": {},
            "url": {
              "path": [
                "payouts",
                "refunds"
              ],
              "host": [
                "{{baseUrl}}"
              ],
              "query": [],
              "variable": []
            },
            "method": "GET",
            "auth": null
          },
          "response": [
            {
              "id": "a260791d-6b34-4e01-a7f5-dd79a83a5833",
              "name": "Refunds",
              "originalRequest": {
                "url": {
                  "path": [
                    "payouts",
                    "refunds"
                  ],
                  "host": [
                    "{{baseUrl}}"
                  ],
                  "query": [],
                  "variable": []
                },
                "header": [
                  {
                    "description": {
                      "content": "Added as a part of security scheme: bearer",
                      "type": "text/plain"
                    },
                    "key": "Authorization",
                    "value": "Bearer <token>"
                  }
                ],
                "method": "GET",
                "body": {}
              },
              "status": "OK",
              "code": 200,
              "header": [
                {
                  "key": "Content-Type",
                  "value": "text/plain"
                }
              ],
              "body": "",
              "cookie": [],
              "_postman_previewlanguage": "text"
            }
          ],
          "event": [],
          "protocolProfileBehavior": {
            "disableBodyPruning": true
          }
        },
        {
          "id": "f6ab9ea8-3df8-4e1b-9cf9-db0d487ccab7",
          "name": "Lean Create Refund",
          "request": {
            "name": "Lean Create Refund",
            "description": {},
            "url": {
              "path": [
                "payouts",
                "refunds"
              ],
              "host": [
                "{{baseUrl}}"
              ],
              "query": [],
              "variable": []
            },
            "header": [
              {
                "key": "Content-Type",
                "value": "application/json"
              }
            ],
            "method": "POST",
            "auth": null,
            "body": {
              "mode": "raw",
              "raw": "{\n  \"payment_id\": \"<uuid>\",\n  \"amount\": \"<number>\",\n  \"reason_code\": \"<string>\",\n  \"currency\": \"<string>\",\n  \"description\": \"<string>\",\n  \"idempotency_key\": \"<string>\"\n}",
              "options": {
                "raw": {
                  "language": "json"
                }
              }
            }
          },
          "response": [
            {
              "id": "404946cd-b0dc-41df-8546-2a45d2c41230",
              "name": "Refund created",
              "originalRequest": {
                "url": {
                  "path": [
                    "payouts",
                    "refunds"
                  ],
                  "host": [
                    "{{baseUrl}}"
                  ],
                  "query": [],
                  "variable": []
                },
                "header": [
                  {
                    "description": {
                      "content": "Added as a part of security scheme: bearer",
                      "type": "text/plain"
                    },
                    "key": "Authorization",
                    "value": "Bearer <token>"
                  }
                ],
                "method": "POST",
                "body": {
                  "mode": "raw",
                  "raw": "{\n  \"payment_id\": \"<uuid>\",\n  \"amount\": \"<number>\",\n  \"reason_code\": \"<string>\",\n  \"currency\": \"<string>\",\n  \"description\": \"<string>\",\n  \"idempotency_key\": \"<string>\"\n}",
                  "options": {
                    "raw": {
                      "language": "json"
                    }
                  }
                }
              },
              "status": "Created",
              "code": 201,
              "header": [
                {
                  "key": "Content-Type",
                  "value": "text/plain"
                }
              ],
              "body": "",
              "cookie": [],
              "_postman_previewlanguage": "text"
            }
          ],
          "event": [],
          "protocolProfileBehavior": {
            "disableBodyPruning": true
          }
        },
        {
          "id": "6917c8f3-4333-4f3a-ab55-c289a88b2136",
          "name": "Lean Process Refunds",
          "request": {
            "name": "Lean Process Refunds",
            "description": {},
            "url": {
              "path": [
                "payouts",
                "refunds"
              ],
              "host": [
                "{{baseUrl}}"
              ],
              "query": [],
              "variable": []
            },
            "method": "PUT",
            "auth": null
          },
          "response": [
            {
              "id": "3ee8a462-1e27-4b14-946d-688f448bb794",
              "name": "Refunds processed",
              "originalRequest": {
                "url": {
                  "path": [
                    "payouts",
                    "refunds"
                  ],
                  "host": [
                    "{{baseUrl}}"
                  ],
                  "query": [],
                  "variable": []
                },
                "header": [
                  {
                    "description": {
                      "content": "Added as a part of security scheme: bearer",
                      "type": "text/plain"
                    },
                    "key": "Authorization",
                    "value": "Bearer <token>"
                  }
                ],
                "method": "PUT",
                "body": {}
              },
              "status": "OK",
              "code": 200,
              "header": [
                {
                  "key": "Content-Type",
                  "value": "text/plain"
                }
              ],
              "body": "",
              "cookie": [],
              "_postman_previewlanguage": "text"
            }
          ],
          "event": [],
          "protocolProfileBehavior": {
            "disableBodyPruning": true
          }
        },
        {
          "id": "47e5a0ed-533a-4ca7-9aa9-27776be3f1fd",
          "name": "Lean Get Refund Reasons",
          "request": {
            "name": "Lean Get Refund Reasons",
            "description": {},
            "url": {
              "path": [
                "payouts",
                "refunds",
                "reasons"
              ],
              "host": [
                "{{baseUrl}}"
              ],
              "query": [],
              "variable": []
            },
            "header": [
              {
                "key": "Accept",
                "value": "application/json"
              }
            ],
            "method": "GET",
            "auth": null
          },
          "response": [
            {
              "id": "63500988-24dc-4f91-92ad-d8109811e7f1",
              "name": "Refund reasons",
              "originalRequest": {
                "url": {
                  "path": [
                    "payouts",
                    "refunds",
                    "reasons"
                  ],
                  "host": [
                    "{{baseUrl}}"
                  ],
                  "query": [],
                  "variable": []
                },
                "header": [
                  {
                    "description": {
                      "content": "Added as a part of security scheme: bearer",
                      "type": "text/plain"
                    },
                    "key": "Authorization",
                    "value": "Bearer <token>"
                  },
                  {
                    "key": "Accept",
                    "value": "application/json"
                  }
                ],
                "method": "GET",
                "body": {}
              },
              "status": "OK",
              "code": 200,
              "header": [
                {
                  "key": "Content-Type",
                  "value": "application/json"
                }
              ],
              "body": "[\n  {\n    \"code\": \"string\",\n    \"description\": \"string\"\n  },\n  {\n    \"code\": \"string\",\n    \"description\": \"string\"\n  }\n]",
              "cookie": [],
              "_postman_previewlanguage": "json"
            }
          ],
          "event": [],
          "protocolProfileBehavior": {
            "disableBodyPruning": true
          }
        }
      ],
      "event": []
    }
  ],
  "event": [],
  "variable": [
    {
      "type": "string",
      "value": "https://api2.leantech.me",
      "key": "baseUrl"
    }
  ],
  "auth": {
    "type": "bearer",
    "bearer": [
      {
        "key": "token",
        "value": "{{bearerToken}}"
      }
    ]
  },
  "info": {
    "_postman_id": "aaa669d5-5ee5-43ef-8583-80db6445b2ca",
    "name": "Lean Refunds API",
    "schema": "https://schema.getpostman.com/json/collection/v2.1.0/collection.json",
    "description": {
      "content": "Issue full or partial refunds against prior Pay by Bank payments. List refunds, create a refund, process queued refunds, and retrieve the canonical list of refund reason codes.\n\n\nContact Support:\n Name: Lean Support",
      "type": "text/plain"
    }
  }
}